pysmm/GEE_wrappers.py
pysmm/SVRmodel.p
pysmm/__init__.py
pysmm/derive_SM.py
pysmm/no_GLDAS_decisiontree_GEE__1step.py
pysmm/utils.py
pysmm/tests/__init__.py
pysmm/tests/test_GEE_wrappers.py
pysmm-0.6.1.dist-info/LICENSE
pysmm-0.6.1.dist-info/METADATA
pysmm-0.6.1.dist-info/WHEEL
pysmm-0.6.1.dist-info/top_level.txt
pysmm-0.6.1.dist-info/RECORD
