Metadata-Version: 2.1
Name: pysmm
Version: 0.6.1
Summary: Python Sentinel Soil-Moisture Mapping
Home-page: https://gitlab.inf.unibz.it/Felix.Greifeneder/pysmm
Author: Felix Greifeneder
Author-email: felix.greifeneder@eurac.edu
License: GPLv3
Platform: UNKNOWN
Classifier: License :: OSI Approved :: GNU General Public License v3 (GPLv3)
Classifier: Programming Language :: Python :: 3.7
Requires-Python: >=3.7
Requires-Dist: earthengine-api
Requires-Dist: google-api-python-client
Requires-Dist: google-auth-httplib2
Requires-Dist: google-auth-oauthlib
Requires-Dist: matplotlib
Requires-Dist: numpy
Requires-Dist: pandas
Requires-Dist: pytesmo
Requires-Dist: scikit-learn
Requires-Dist: scipy
